LICENSE
README.md
pyproject.toml
setup.py
holdon/__init__.py
holdon/escapes.py
holdon/progress.py
holdon.egg-info/PKG-INFO
holdon.egg-info/SOURCES.txt
holdon.egg-info/dependency_links.txt
holdon.egg-info/requires.txt
holdon.egg-info/top_level.txt