Metadata-Version: 2.1
Name: holdon
Version: 0.1
Summary: A lightweight Python progress bar library with a simple API.
Author-email: AWeirdDev <aweirdscratcher@gmail.com>
License: MIT License
Project-URL: Homepage, https://github.com/AWeirdScratcher/holdon
Project-URL: Bug Tracker, https://github.com/AWeirdScratcher/holdon/issues
Keywords: holdon,progress-bar,progress,bar,loading,loader
Classifier: Programming Language :: Python :: 3
Classifier: License :: OSI Approved :: MIT License
Classifier: Operating System :: OS Independent
Requires-Python: >=3
License-File: LICENSE
Requires-Dist: requests
